orka_sdk/__init__.py
orka_sdk/gha_controller.py
orka_sdk/images.py
orka_sdk/k8s.py
orka_sdk/nodes.py
orka_sdk/orka_sdk.py
orka_sdk/result.py
orka_sdk/vm.py
orka_sdk-1.0.3.dist-info/LICENSE
orka_sdk-1.0.3.dist-info/METADATA
orka_sdk-1.0.3.dist-info/WHEEL
orka_sdk-1.0.3.dist-info/top_level.txt
orka_sdk-1.0.3.dist-info/RECORD
