Metadata-Version: 2.1
Name: orka-sdk
Version: 1.0.3
Summary: Control Orka clusters and the macOS VMs they run.
Home-page: https://github.com/jeff-vincent/orka-python-sdk
Author: Jeff Vincent
Author-email: jeff.d.vincent@gmail.com
License: MIT
Platform: UNKNOWN
Classifier: License :: OSI Approved :: MIT License
Classifier: Programming Language :: Python :: 3
Classifier: Programming Language :: Python :: 3.8
Classifier: Programming Language :: Python :: 3.9
Classifier: Programming Language :: Python :: 3.10
License-File: LICENSE
Requires-Dist: attrs (==21.4.0)
Requires-Dist: bcrypt (==3.2.0)
Requires-Dist: cachetools (==4.2.4)
Requires-Dist: certifi (==2021.10.8)
Requires-Dist: cffi (==1.15.0)
Requires-Dist: charset-normalizer (==2.0.9)
Requires-Dist: cryptography (==36.0.0)
Requires-Dist: google-auth (==2.3.3)
Requires-Dist: idna (==3.3)
Requires-Dist: importlib-metadata (==4.10.1)
Requires-Dist: iniconfig (==1.1.1)
Requires-Dist: Jinja2 (==3.0.3)
Requires-Dist: kubernetes (==21.7.0)
Requires-Dist: MarkupSafe (==2.0.1)
Requires-Dist: mock (==4.0.3)
Requires-Dist: oauthlib (==3.1.1)
Requires-Dist: packaging (==21.3)
Requires-Dist: paramiko (==2.8.1)
Requires-Dist: pluggy (==1.0.0)
Requires-Dist: py (==1.11.0)
Requires-Dist: pyasn1 (==0.4.8)
Requires-Dist: pyasn1-modules (==0.2.8)
Requires-Dist: pycparser (==2.21)
Requires-Dist: PyNaCl (==1.4.0)
Requires-Dist: pyparsing (==3.0.7)
Requires-Dist: pytest (==6.2.5)
Requires-Dist: python-dateutil (==2.8.2)
Requires-Dist: PyYAML (==6.0)
Requires-Dist: requests (==2.26.0)
Requires-Dist: requests-oauthlib (==1.3.0)
Requires-Dist: rsa (==4.8)
Requires-Dist: six (==1.16.0)
Requires-Dist: toml (==0.10.2)
Requires-Dist: typing-extensions (==4.0.1)
Requires-Dist: urllib3 (==1.26.7)
Requires-Dist: websocket-client (==1.2.3)
Requires-Dist: zipp (==3.7.0)
